etc/__init__.py
etc/get_git_version.py
eu/__init__.py
eu/softfire/__init__.py
eu/softfire/tub/__init__.py
eu/softfire/tub/api/Api.py
eu/softfire/tub/api/__init__.py
eu/softfire/tub/core/CoreManagers.py
eu/softfire/tub/core/__init__.py
eu/softfire/tub/core/calendar.py
eu/softfire/tub/core/certificate.py
eu/softfire/tub/entities/__init__.py
eu/softfire/tub/entities/entities.py
eu/softfire/tub/entities/repositories.py
eu/softfire/tub/exceptions/__init__.py
eu/softfire/tub/exceptions/exceptions.py
eu/softfire/tub/main/ExperimentManager.py
eu/softfire/tub/main/__init__.py
eu/softfire/tub/main/configuration.py
eu/softfire/tub/messaging/MessagingAgent.py
eu/softfire/tub/messaging/__init__.py
eu/softfire/tub/messaging/grpc/__init__.py
eu/softfire/tub/messaging/grpc/messages_pb2.py
eu/softfire/tub/messaging/grpc/messages_pb2_grpc.py
eu/softfire/tub/utils/__init__.py
eu/softfire/tub/utils/static_config.py
eu/softfire/tub/utils/utils.py
experiment_manager-1.4.6.data/scripts/experiment-manager
experiment_manager-1.4.6.dist-info/DESCRIPTION.rst
experiment_manager-1.4.6.dist-info/METADATA
experiment_manager-1.4.6.dist-info/RECORD
experiment_manager-1.4.6.dist-info/WHEEL
experiment_manager-1.4.6.dist-info/metadata.json
experiment_manager-1.4.6.dist-info/top_level.txt
tests/__init__.py
tests/csar_test.py
tests/grpc_test.py
