Metadata-Version: 2.0
Name: experiment-manager
Version: 1.4.6
Summary: The SoftFIRE Experimenter Manager
Home-page: http://softfire.eu/
Author: Lorenzo Tomasini
Author-email: lorenzo.tomasini@gmail.com
License: Apache 2
Keywords: python vnfm nfvo open baton openbaton sdk experiment manager softfire tosca openstack rest
Platform: UNKNOWN
Classifier: Development Status :: 4 - Beta
Classifier: Intended Audience :: Developers
Classifier: Intended Audience :: Science/Research
Classifier: Programming Language :: Python :: 3.5
Classifier: License :: OSI Approved :: Apache Software License
Classifier: Framework :: Bottle
Classifier: Framework :: AsyncIO
Requires-Dist: tosca-parser
Requires-Dist: bottle
Requires-Dist: beaker
Requires-Dist: paste
Requires-Dist: bottle-cork
Requires-Dist: sqlalchemy
Requires-Dist: grpcio
Requires-Dist: dateparser
Requires-Dist: pyOpenSSL
Requires-Dist: PyYAML
Requires-Dist: mysqlclient
